parallize/__init__.py
parallize-0.1.5.dist-info/LICENSE
parallize-0.1.5.dist-info/METADATA
parallize-0.1.5.dist-info/WHEEL
parallize-0.1.5.dist-info/entry_points.txt
parallize-0.1.5.dist-info/RECORD
