Metadata-Version: 2.1
Name: parallize
Version: 0.1.5
Summary: Parallize is a Python package that provides utilities to parallelize both synchronous and asynchronous functions using the `concurrent.futures.ProcessPoolExecutor`.
Author: vikyw89
Author-email: vikyw89@gmail.com
Requires-Python: >=3.10,<4.0
Classifier: Programming Language :: Python :: 3
Classifier: Programming Language :: Python :: 3.10
Classifier: Programming Language :: Python :: 3.11
Classifier: Programming Language :: Python :: 3.12
